LICENSE
setup.py
mailfilter/__init__.py
mailfilter/mailFilter.py
mailfilter.egg-info/PKG-INFO
mailfilter.egg-info/SOURCES.txt
mailfilter.egg-info/dependency_links.txt
mailfilter.egg-info/entry_points.txt
mailfilter.egg-info/requires.txt
mailfilter.egg-info/top_level.txt