Metadata-Version: 1.1
Name: mailfilter
Version: 0.1.dev
Summary: Filter HTML and blacklisted attachments.
Home-page: http://www.fixedpoint.nl
Author: Jeroen F.J. Laros
Author-email: jlaros@fixedpoint.nl
License: MIT License
Keywords: mail html blacklist filter
Platform: any
Classifier: Development Status :: 3 - Alpha
Classifier: Operating System :: OS Independent
Classifier: Programming Language :: Python
Requires: Levenshtein
Requires: email
